joft/__init__.py
joft/actions.py
joft/base.py
joft/cli.py
joft/models.py
joft/utils.py
joft-0.1.1.dist-info/LICENSE
joft-0.1.1.dist-info/METADATA
joft-0.1.1.dist-info/WHEEL
joft-0.1.1.dist-info/entry_points.txt
joft-0.1.1.dist-info/top_level.txt
joft-0.1.1.dist-info/RECORD
