Metadata-Version: 2.1
Name: joft
Version: 0.1.1
Summary: CLI tool for automation of user actions on a JIRA instance
Author-email: Martin Curlej <mcurlej@redhat.com>
Requires-Python: >=3.11
License-File: LICENSE
Requires-Dist: jira >=3.6.0
Requires-Dist: click >=8.1.7
Requires-Dist: pyyaml >=6.0.1
Requires-Dist: tabulate >=0.9.0
Requires-Dist: platformdirs >=4.2.2
Provides-Extra: dev
Requires-Dist: tox >=4.16.0 ; extra == 'dev'
Provides-Extra: lint
Requires-Dist: ruff >=0.6.2 ; extra == 'lint'
Provides-Extra: test
Requires-Dist: pytest >=8.1.1 ; extra == 'test'
Provides-Extra: type
Requires-Dist: mypy >=1.11.1 ; extra == 'type'
Requires-Dist: types-PyYAML >=6.0.12.20240724 ; extra == 'type'
Requires-Dist: types-tabulate >=0.9.0.20240106 ; extra == 'type'
